recaptcha_solver/__init__.py
recaptcha_solver/click_img/__init__.py
recaptcha_solver/click_img/click_fig_center.py
recaptcha_solver/click_img/click_fig_left.py
recaptcha_solver/human_style/__init__.py
recaptcha_solver/human_style/human_digite.py
recaptcha_solver/human_style/time_by_img.py
recaptcha_solver-1.0.4.dist-info/LICENSE
recaptcha_solver-1.0.4.dist-info/METADATA
recaptcha_solver-1.0.4.dist-info/WHEEL
recaptcha_solver-1.0.4.dist-info/top_level.txt
recaptcha_solver-1.0.4.dist-info/RECORD
