Metadata-Version: 2.1
Name: recaptcha-solver
Version: 1.0.4
Summary: UNKNOWN
Home-page: https://github.com/BrunoASNascimento/recaptcha_solver
Author: Bruno Nascimento
Author-email: bruno_freddy@hotmail.com
License: GPL
Project-URL: Código fonte, https://github.com/BrunoASNascimento/recaptcha_solver
Project-URL: Download, https://github.com/BrunoASNascimento/recaptcha_solver/archive/refs/heads/main.zip
Keywords: recaptcha_solver,recaptcha
Platform: UNKNOWN
Classifier: Development Status :: 5 - Production/Stable
Classifier: Intended Audience :: Developers
Classifier: License :: OSI Approved :: GNU General Public License v3 (GPLv3)
Classifier: Natural Language :: Portuguese (Brazilian)
Classifier: Operating System :: OS Independent
Classifier: Topic :: Software Development :: Internationalization
Requires-Python: >=3.8
